gentle/__init__.py
gentle/__main__.py
gentle/py.typed
gentle/utils.py
gentle/generators/__init__.py
gentle/generators/autoconf.py
gentle/generators/bower.py
gentle/generators/cargo.py
gentle/generators/composer.py
gentle/generators/cpan.py
gentle/generators/doap.py
gentle/generators/gemspec.py
gentle/generators/hpack.py
gentle/generators/npm.py
gentle/generators/nuspec.py
gentle/generators/pear.py
gentle/generators/pom.py
gentle/generators/pubspec.py
gentle/generators/shards.py
gentle/generators/python/__init__.py
gentle/generators/python/pkg_info.py
gentle/generators/python/pyproject.py
gentle/generators/python/setuptools.py
gentle/generators/python/wheel.py
gentle/metadata/__init__.py
gentle/metadata/types.py
gentle/metadata/utils.py
gentle/pms/__init__.py
gentle/pms/portagepm.py
gentle_mxml-1.0.2.dist-info/entry_points.txt
gentle_mxml-1.0.2.dist-info/LICENSE
gentle_mxml-1.0.2.dist-info/WHEEL
gentle_mxml-1.0.2.dist-info/METADATA
gentle_mxml-1.0.2.dist-info/RECORD
