Metadata-Version: 2.3
Name: gentle-mxml
Version: 1.0.2
Summary: Gentoo Metadata XML generator
Keywords: gentoo,ebuild,metadata,upstream,maintainer
Author-email: Anna <cyber@sysrq.in>
Requires-Python: >=3.11
Classifier: Development Status :: 5 - Production/Stable
Classifier: Environment :: Console
Classifier: Intended Audience :: Developers
Classifier: License :: DFSG approved
Classifier: Operating System :: POSIX
Classifier: Programming Language :: Python :: 3 :: Only
Classifier: Topic :: System :: Software Distribution
Classifier: Topic :: Utilities
Classifier: Typing :: Typed
Requires-Dist: portage
Requires-Dist: lxml
Requires-Dist: insipid-sphinx-theme ; extra == "docs"
Requires-Dist: sphinx ; extra == "docs"
Requires-Dist: sphinx-prompt ; extra == "docs"
Requires-Dist: pkginfo ; extra == "pkginfo"
Requires-Dist: rdflib ; extra == "rdf"
Requires-Dist: pytest ; extra == "test"
Requires-Dist: xmldiff ; extra == "test"
Requires-Dist: build[uv]>=1.2.0 ; extra == "wheel"
Requires-Dist: pyproject_hooks ; extra == "wheel"
Requires-Dist: PyYAML ; extra == "yaml"
Project-URL: Changelog, https://gentle.sysrq.in/release-notes.html
Project-URL: Home, https://gentle.sysrq.in
Project-URL: Issues, https://bugs.sysrq.in/enter_bug.cgi?product=Software&component=gentle
Project-URL: Source, https://git.sysrq.in/gentle
Provides-Extra: docs
Provides-Extra: pkginfo
Provides-Extra: rdf
Provides-Extra: test
Provides-Extra: wheel
Provides-Extra: yaml
